SplatTextGame/__init__.py
SplatTextGame/splatcode.py
Splat_TextGame/__init__.py
Splat_TextGame/splatcode.py
SplatApp-1.1.8.dist-info/LICENSE
SplatApp-1.1.8.dist-info/METADATA
SplatApp-1.1.8.dist-info/WHEEL
SplatApp-1.1.8.dist-info/top_level.txt
SplatApp-1.1.8.dist-info/zip-safe
SplatApp-1.1.8.dist-info/RECORD
